heapprint/__init__.py
heapprint/heap.py
heapprint-0.0.2.dist-info/licenses/LICENSE
heapprint-0.0.2.dist-info/METADATA
heapprint-0.0.2.dist-info/WHEEL
heapprint-0.0.2.dist-info/top_level.txt
heapprint-0.0.2.dist-info/RECORD
