Metadata-Version: 2.4
Name: heapprint
Version: 0.0.2
Summary: Heap (ikkilik daraxt) tuzilishini vizual ko'rsatish uchun Python kutubxonasi
Author: Jasur Omanov
License: MIT
Classifier: License :: OSI Approved :: MIT License
Classifier: Programming Language :: Python :: 3
Classifier: Operating System :: OS Independent
Requires-Python: >=3.6
License-File: LICENSE
Dynamic: author
Dynamic: classifier
Dynamic: description
Dynamic: description-content-type
Dynamic: license
Dynamic: license-file
Dynamic: requires-python
Dynamic: summary
